spidey/__init__.py
spidey/__main__.py
spidey/main.py
spidey.py-0.4.5.dist-info/DESCRIPTION.rst
spidey.py-0.4.5.dist-info/entry_points.txt
spidey.py-0.4.5.dist-info/METADATA
spidey.py-0.4.5.dist-info/metadata.json
spidey.py-0.4.5.dist-info/RECORD
spidey.py-0.4.5.dist-info/top_level.txt
spidey.py-0.4.5.dist-info/WHEEL
