Metadata-Version: 2.0
Name: spidey.py
Version: 0.4.5
Summary: Web spiders are usually disliked by websites, but useful for recursive API/page downloads for offline analysis.
Home-page: https://github.com/khilnani/spidey.py
Author: khilnani
Author-email: nik@khilnani.org
License: MIT
Keywords: web,api,downloader,spider,crawler
Platform: UNKNOWN
Classifier: Development Status :: 3 - Alpha
Classifier: Environment :: Console
Classifier: Environment :: Console
Classifier: Intended Audience :: Developers
Classifier: Intended Audience :: System Administrators
Classifier: License :: OSI Approved :: MIT License
Classifier: Operating System :: MacOS :: MacOS X
Classifier: Operating System :: Unix
Classifier: Operating System :: POSIX
Classifier: Programming Language :: Python
Classifier: Programming Language :: Python :: 2.7
Classifier: Topic :: Software Development
Classifier: Topic :: Software Development :: Libraries
Classifier: Topic :: Software Development :: Libraries :: Python Modules
Requires-Dist: requests
